dbnl_bear/__init__.py
dbnl_bear/ai_read.py
dbnl_bear/overview.py
dbnl_bear/parse.py
dbnl_bear-0.4.1.dist-info/METADATA
dbnl_bear-0.4.1.dist-info/WHEEL
dbnl_bear-0.4.1.dist-info/top_level.txt
dbnl_bear-0.4.1.dist-info/RECORD
