Metadata-Version: 2.1
Name: dbnl_bear
Version: 0.4.1
Summary: A Python package to use an AI assistant for historical analysis
Home-page: https://github.com/trister95/dbnl_bear
Author: Arjan van Dalfsen
Author-email: j.a.vandalfsen@uu.nl
Classifier: Programming Language :: Python :: 3
Classifier: Operating System :: OS Independent
Requires-Python: >=3.10
Requires-Dist: lxml
Requires-Dist: tqdm
Requires-Dist: python-dotenv
Requires-Dist: langchain-core
Requires-Dist: langchain-openai
Requires-Dist: typing
Requires-Dist: langchain-text-splitters
Requires-Dist: docx
Requires-Dist: fuzzywuzzy
Requires-Dist: pydantic
Requires-Dist: python-docx
Requires-Dist: python-Levenshtein
